btviewer/__init__.py
btviewer/__main__.py
btviewer/app.py
btviewer/app_factory.py
btviewer/mixins.py
btviewer/blueprints/__init__.py
btviewer/blueprints/label/__init__.py
btviewer/blueprints/label/model.py
btviewer/blueprints/label/views.py
btviewer/blueprints/photo/__init__.py
btviewer/blueprints/photo/model.py
btviewer/blueprints/photo/views.py
btviewer/blueprints/session/__init__.py
btviewer/blueprints/session/models.py
btviewer/blueprints/session/views.py
btviewer/static/UOSLogo_Primary_Violet_RGB_logo.svg
btviewer/static/index.html
btviewer/static/assets/index-CfJNB6ax.css
btviewer/static/assets/index-oQfhO6PT.js
btviewer-0.0.1rc16.dist-info/LICENSE
btviewer-0.0.1rc16.dist-info/METADATA
btviewer-0.0.1rc16.dist-info/WHEEL
btviewer-0.0.1rc16.dist-info/entry_points.txt
btviewer-0.0.1rc16.dist-info/top_level.txt
btviewer-0.0.1rc16.dist-info/RECORD
