Metadata-Version: 2.1
Name: btviewer
Version: 0.0.1rc16
Summary: Web app for human labelling of tracking images
Author-email: Mike Smith <m.t.smith@sheffield.ac.uk>, Joe Heffer <joe.heffer@sheffield.ac.uk>, Shi Min Chua <s.chua@sheffield.ac.uk>
Maintainer-email: Mike Smith <m.t.smith@sheffield.ac.uk>
License: GNU GENERAL PUBLIC LICENSE
Project-URL: Homepage, https://pypi.org/project/btviewer
Project-URL: Bug_Tracker, https://github.com/SheffieldMLtracking/btviewer/issues
Project-URL: Documentation, https://github.com/SheffieldMLtracking/btviewer/blob/main/README.md
Project-URL: Repository, https://github.com/SheffieldMLtracking/btviewer
Project-URL: Changelog, https://github.com/SheffieldMLtracking/btviewer/releases
Keywords: bee,small animals,tracking
Classifier: Development Status :: 4 - Beta
Classifier: Programming Language :: Python :: 3
Classifier: License :: OSI Approved :: MIT License
Classifier: Operating System :: OS Independent
Requires-Python: >=3.8
License-File: LICENSE
Requires-Dist: flask ==3.*
Requires-Dist: waitress ==3.*
Requires-Dist: pillow ==10.*
Requires-Dist: numpy ==1.*
Provides-Extra: test
Requires-Dist: flake8 ; extra == 'test'
Requires-Dist: pytest ; extra == 'test'
